easy_ioc/__init__.py
easy_ioc/inject.py
easy_ioc/injectable.py
easy_ioc/ioc.py
easy_ioc-0.1.4.dist-info/LICENSE
easy_ioc-0.1.4.dist-info/METADATA
easy_ioc-0.1.4.dist-info/WHEEL
easy_ioc-0.1.4.dist-info/top_level.txt
easy_ioc-0.1.4.dist-info/RECORD
